{
  "type": "Feature",
  "properties": {
    "date:cessation_lower": "2021-12-01",
    "date:cessation_upper": "2021-12-01",
    "date:inception_lower": "2021-11-09",
    "date:inception_upper": "2021-11-09",
    "flysfo:url": "https://www.sfomuseum.org/video-arts/powwow",
    "sfo:level": -1,
    "sfomuseum:description": "British-born filmmaker Keeley Gould produces a neon-hued portrait of the diverse participants attending the Gathering of Nations Powwow, an annual celebration of Native American culture held in Albuquerque, New Mexico.",
    "sfomuseum:has_brochure": 0,
    "sfomuseum:has_catalog": 0,
    "sfomuseum:on_display": 0,
    "sfomuseum:placetype": "exhibition",
    "sfomuseum:post_security": 0,
    "sfomuseum:type": "Video Art",
    "wof:name": "Pow Wow (2021-2)",
    "wof:placetype": "installation",
    "wof:placetype_alt": "exhibition"
  },
  "geometry": {"coordinates":[-122.37385309950533,37.61939390848619],"type":"Point"}
}
