{
  "type": "Feature",
  "properties": {
    "date:cessation_lower": "2022-03-31",
    "date:cessation_upper": "2022-03-31",
    "date:inception_lower": "2022-03-01",
    "date:inception_upper": "2022-03-01",
    "flysfo:url": "https://www.sfomuseum.org/exhibitions/above-sfo-aerial-photography-marshall-moxom",
    "sfo:level": -1,
    "sfomuseum:has_brochure": 0,
    "sfomuseum:has_catalog": 0,
    "sfomuseum:on_display": 1,
    "sfomuseum:placetype": "exhibition",
    "sfomuseum:post_security": 0,
    "sfomuseum:type": "Photography",
    "wof:name": "Marshall Moxom: Four Views of San Francisco International Airport",
    "wof:placetype": "installation",
    "wof:placetype_alt": "exhibition"
  },
  "geometry": {"coordinates":[-122.37385309950533,37.61939390848619],"type":"Point"}
}
