{
  "type": "Feature",
  "properties": {
    "date:cessation_lower": "2020-11-22",
    "date:cessation_upper": "2020-11-22",
    "date:inception_lower": "2020-05-01",
    "date:inception_upper": "2020-05-31",
    "sfomuseum:has_brochure": 0,
    "sfomuseum:has_catalog": 0,
    "sfomuseum:hashtag": "x",
    "sfomuseum:is_current": 0,
    "sfomuseum:on_display": 0,
    "sfomuseum:placetype": "exhibition",
    "sfomuseum:type": "Aviation",
    "wof:label": "On Silent Wings: Published Works on Gliding and Soaring Flight (2020-~05)",
    "wof:name": "On Silent Wings: Published Works on Gliding and Soaring Flight",
    "wof:placetype": "installation",
    "wof:placetype_alt": [
      "exhibition"
    ]
  },
  "geometry": {"coordinates":[-122.37385309950533,37.61939390848619],"type":"Point"}
}
