{
  "type": "Feature",
  "properties": {
    "date:inception_lower": "2025-10-11",
    "date:inception_upper": "2025-10-11",
    "millsfield:count_collection_objects": 28,
    "sfo:level": -1,
    "sfomuseum:date_start": "2025-10-11",
    "sfomuseum:description": "Reproduction graphics from SFOM Archives Collection.",
    "sfomuseum:has_brochure": 0,
    "sfomuseum:has_catalog": 0,
    "sfomuseum:on_display": 1,
    "sfomuseum:placetype": "exhibition",
    "sfomuseum:post_security": -1,
    "sfomuseum:type": "NonAviation",
    "wof:name": "Special Exhibit: C3C Executive Office Graphics, Phase 1",
    "wof:placetype": "installation",
    "wof:placetype_alt": "exhibition"
  },
  "geometry": {"type":"Point","coordinates":[-122.37385309950533,37.61939390848619]}
}
